__version__.py
wattrex_battery_cycler_datatypes/comm_data/__init__.py
wattrex_battery_cycler_datatypes/comm_data/comm_data.py
wattrex_battery_cycler_datatypes/cycler_data/__init__.py
wattrex_battery_cycler_datatypes/cycler_data/cycler_data_battery.py
wattrex_battery_cycler_datatypes/cycler_data/cycler_data_common.py
wattrex_battery_cycler_datatypes/cycler_data/cycler_data_device.py
wattrex_battery_cycler_datatypes/cycler_data/cycler_data_experiment.py
wattrex_battery_cycler_datatypes-0.0.15.dist-info/LICENSE.txt
wattrex_battery_cycler_datatypes-0.0.15.dist-info/METADATA
wattrex_battery_cycler_datatypes-0.0.15.dist-info/WHEEL
wattrex_battery_cycler_datatypes-0.0.15.dist-info/top_level.txt
wattrex_battery_cycler_datatypes-0.0.15.dist-info/RECORD
